rtl/integration/activation_unit.v
//=============================================================================
// File        : activation_unit.v
// Description : Activation Unit for Gated Convolution (DeepFill v2) based NPU
//               - track_sel = 0 : ReLU        (Feature track)
//               - track_sel = 1 : Sigmoid PLAN (Gate track, Piece-wise Linear Approx.)
//
// Design Notes:
//   - Fixed-point format : Q(DATA_WIDTH-FRAC_WIDTH).FRAC_WIDTH, signed 2's complement
//     (Default: Q8.8 -> 16bit total, 8bit integer(incl. sign), 8bit fraction)
//   - No multiplier / divider used. Only Adder, Mux, Shifter (Synthesis-friendly)
//   - 1-stage output pipeline register inserted to cut the critical path
//=============================================================================

module activation_unit #(
    parameter DATA_WIDTH = 16,   // Total bit-width of data (signed)
    parameter FRAC_WIDTH = 8     // Fractional bit-width (Q format)
)(
    input  wire                    clk,
    input  wire                    reset_n,    // Active-low async reset
    input  wire                    enable,     // Module enable

    input  wire                    track_sel,  // 0: ReLU(Feature) / 1: Sigmoid(Gate)
    input  wire signed [DATA_WIDTH-1:0] data_in,
    input  wire                    valid_in,

    output reg  signed [DATA_WIDTH-1:0] data_out,
    output reg                     valid_out
);

    //-------------------------------------------------------------------
    // Local Parameters : Fixed-point constants derived from FRAC_WIDTH
    //-------------------------------------------------------------------
    // Sigmoid PLAN breakpoints : x = -4.0, x = +4.0 in Q format
    localparam signed [DATA_WIDTH-1:0] NEG_THRESHOLD = -(32'sd4 <<< FRAC_WIDTH); // -4.0
    localparam signed [DATA_WIDTH-1:0] POS_THRESHOLD =  (32'sd4 <<< FRAC_WIDTH); //  4.0

    // Output saturation constants
    localparam signed [DATA_WIDTH-1:0] FP_ZERO = {DATA_WIDTH{1'b0}};            //  0.0
    localparam signed [DATA_WIDTH-1:0] FP_ONE  =  (32'sd1 <<< FRAC_WIDTH);      //  1.0
    localparam signed [DATA_WIDTH-1:0] FP_HALF =  (32'sd1 <<< (FRAC_WIDTH-1));  //  0.5

    //-------------------------------------------------------------------
    // Stage 0 (Combinational) : Activation Function Computation
    //-------------------------------------------------------------------
    reg signed [DATA_WIDTH-1:0] relu_result;
    reg signed [DATA_WIDTH-1:0] sigmoid_result;
    reg signed [DATA_WIDTH-1:0] act_result_comb;

    // Intermediate wire for PLAN linear segment: (x >> 3) + 0.5
    // Using arithmetic shift (>>>) on signed data to preserve sign (no multiplier/divider)
    wire signed [DATA_WIDTH-1:0] shifted_x;
    assign shifted_x = data_in >>> 3; // equivalent to x / 8, hardware-friendly (single shifter)

    //--------------------------------------
    // ReLU (track_sel == 0)
    //--------------------------------------
    always @(*) begin
        // Check MSB (sign bit) only -> negative number => 0, else pass-through
        if (data_in[DATA_WIDTH-1] == 1'b1)
            relu_result = FP_ZERO;
        else
            relu_result = data_in;
    end

    //--------------------------------------
    // Sigmoid PLAN (track_sel == 1)
    // x <  -4        -> 0
    // -4 <= x < 4     -> (x >> 3) + 0.5
    // x >=  4        -> 1
    //--------------------------------------
    always @(*) begin
        if (data_in < NEG_THRESHOLD)
            sigmoid_result = FP_ZERO;
        else if (data_in >= POS_THRESHOLD)
            sigmoid_result = FP_ONE;
        else
            sigmoid_result = shifted_x + FP_HALF; // Adder + Shifter only
    end

    //--------------------------------------
    // Track Selection MUX
    //--------------------------------------
    always @(*) begin
        case (track_sel)
            1'b0:    act_result_comb = relu_result;     // Feature track
            1'b1:    act_result_comb = sigmoid_result;   // Gate track
            default: act_result_comb = relu_result;
        endcase
    end

    //-------------------------------------------------------------------
    // Stage 1 (Sequential) : Output Pipeline Register
    // - Cuts critical path between combinational activation logic
    //   and the next stage (Pipeline Matcher)
    // - Async active-low reset
    //-------------------------------------------------------------------
    always @(posedge clk or negedge reset_n) begin
        if (!reset_n) begin
            data_out  <= {DATA_WIDTH{1'b0}};
            valid_out <= 1'b0;
        end
        else if (enable) begin
            data_out  <= act_result_comb;
            valid_out <= valid_in;
        end
        else begin
            // When disabled, hold output value but drop valid to avoid
            // downstream misinterpretation of stale data
            valid_out <= 1'b0;
        end
    end

endmodule

rtl/integration/mac_to_q88_bridge.v
`timescale 1ns / 1ps
//=============================================================================
// File        : mac_to_q88_bridge.v
// Description : pe_ctrl 의 32bit 정수 saturation 결과(conv_out)를
//               activation_unit 이 요구하는 16bit Q8.8 고정소수점 포맷으로
//               변환하는 조합회로 브릿지
//
// Design Notes (비트 슬라이스/스케일링 근거):
//   pe_ctrl 은 mode_int4 에 따라 아래의 정수 상한/하한으로 saturation 함:
//       INT4 : +-2047    (2^11-1, 부호 포함 12bit 필요)
//       INT8 : +-524287  (2^19-1, 부호 포함 20bit 필요)
//
//   activation_unit 이 기대하는 Q8.8 은 16bit 전체 중 8bit 정수부(부호 포함)
//   + 8bit 소수부이며, 표현 가능한 최대값은 +32767(=+127.996), 최소값은
//   -32768(=-128.0) 입니다.
//
//   두 모드의 saturation 경계값이 서로 자릿수가 크게 다르므로, 단순히
//   32bit 중 [15:0] 을 그대로 잘라내면(단순 truncation)
//     - INT4 모드: 유효 비트가 12bit뿐이라 Q8.8 의 소수부 해상도를 거의
//       못 씀 (다이나믹 레인지 낭비)
//     - INT8 모드: 상위 유효 비트가 그대로 잘려나가 값이 깨짐(overflow)
//   두 문제가 동시에 발생합니다.
//
//   따라서 saturation 경계값이 Q8.8 의 최대 표현값(32767)에 최대한
//   근접하도록 "모드별 정렬 시프트(SHIFT_AMT=4)"를 적용합니다.
//
//     INT4 :  2047 <<< 4  = 32752  (~ +127.97 in Q8.8) -> 좌측 시프트
//             (작은 다이나믹 레인지를 16bit 폭에 맞춰 확장 -> 소수부 해상도 확보)
//     INT8 : 524287 >>> 4 = 32767  (~ +127.996 in Q8.8) -> 우측 시프트
//             (20bit 다이나믹 레인지를 16bit 로 압축 -> 상위 유효비트 보존)
//
//   즉, 시프트 이후에는 항상 |value| <= 32767 이 보장되므로, 상위
//   [31:16] 비트는 부호확장 비트만 남게 되고 이를 버리는 [15:0] 슬라이스는
//   "정보 손실이 없는(lossless) 슬라이스"가 됩니다.
//
//   주의(설계 가정): 이 스케일은 MAC 누산기의 이진소수점이 LSB에
//   위치한(순수 정수 누산) 것을 가정한 것입니다. 실제 가중치/활성화
//   양자화 스케일(예: weight 가 Qm.n 포맷인 경우)이 다르면 SHIFT_AMT 및
//   모드별 시프트 방향은 반드시 재검증/재계산되어야 합니다.
//
//   방어적 saturation: pe_ctrl 단계에서 이미 |conv_out| <= target_max 가
//   보장되고 SHIFT_AMT 도 이를 감안해 선택했지만, 향후 target_max/min
//   값이 변경되고 SHIFT_AMT 가 함께 갱신되지 않는 실수(설계 변경 누락)에
//   대비해 2차 saturation을 한번 더 넣어 16bit 슬라이스 시 부호反전
//   (wraparound) 사고를 원천 차단합니다.
//=============================================================================
module mac_to_q88_bridge #(
    parameter DATA_WIDTH = 16,
    parameter FRAC_WIDTH = 8
)(
    input  wire signed [31:0]            conv_out,   // pe_ctrl 의 saturated 32bit 정수 결과
    input  wire                          mode_int4,  // 1: INT4 모드 / 0: INT8 모드
    output wire signed [DATA_WIDTH-1:0]  data_q88    // activation_unit 입력용 Q8.8
);

    localparam integer SHIFT_AMT = 4;

    // 모드별 정렬 시프트 (조합회로, 산술 시프트로 부호 보존)
    wire signed [31:0] shifted_val;
    assign shifted_val = mode_int4 ? (conv_out <<< SHIFT_AMT)   // INT4 : 좌측 시프트(scale up)
                                    : (conv_out >>> SHIFT_AMT); // INT8 : 우측 시프트(scale down)

    // 방어적 2차 saturation (Q8.8 16bit 부호 범위로 clip)
    localparam signed [31:0] Q88_MAX = 32'sd32767;   // 16bit signed max
    localparam signed [31:0] Q88_MIN = -32'sd32768;  // 16bit signed min

    wire signed [31:0] clipped_val;
    assign clipped_val = (shifted_val > Q88_MAX) ? Q88_MAX :
                          (shifted_val < Q88_MIN) ? Q88_MIN :
                          shifted_val;

    // 최종 슬라이스 : 위에서 이미 16bit 부호범위로 clip 했으므로
    // 상위 [31:16] 은 부호확장 비트 뿐 -> 하위 16bit 슬라이스는 무손실.
    assign data_q88 = clipped_val[DATA_WIDTH-1:0];

endmodule

rtl/integration/pe_ctrl.v
`timescale 1ns / 1ps

module pe_ctrl (
    // [1. 시스템 기본 신호]
    input wire clk,                // 100MHz 가상 클록 (주기 10ns)
    input wire reset,              // Active-High 리셋 (1일 때 초기화)
    input wire mode_int4,          // 1: INT4 모드, 0: INT8 모드 (가변 정밀도 제어 신호)

    // [2. 내부 모듈 인터페이스 (from pe_mac.v)]
    // TODO: MAC과 비트 폭([31:0]) 및 valid 의미 재확인
    input wire signed [31:0] mac_result, // MAC 연산부에서 bias까지 더해져 나온 결과값, 32비트
    input wire valid_d,                  // MAC에서 보내준 연산 완료 타이밍 신호

    // [3. 외부 모듈 인터페이스 (to Activation Unit)]
    output reg signed [31:0] conv_out,  // 파이프라인/출력 레지스터
    output reg valid_out                // Activation Unit을 깨우는 연산 완료 신호
);

    // -------------------------------------------------------------------------
    // 가변 정밀도(INT4 / INT8) 모드별 임계값(Threshold) 설정
    // -------------------------------------------------------------------------
    wire signed [31:0] target_max;
    wire signed [31:0] target_min;

    // mode_int4 신호에 따라 상한선/하한선을 다르게 스위칭 (조합회로)
    assign target_max = mode_int4 ? 32'sd2047 : 32'sd524287;
    assign target_min = mode_int4 ? -32'sd2047 : -32'sd524287;

    // -------------------------------------------------------------------------
    // Overflow & Saturation (포화) 처리 (조합회로)
    // -------------------------------------------------------------------------
    // 설명: mac_result가 한계치를 넘을 때, 값이 뒤집히지 않도록
    //      최댓값/최솟값으로 고정 (Signed 연산 주의: sd 사용)

    wire signed [31:0] saturated_result;

    // 조건 연산자를 이용한 포화 처리 예시
    assign saturated_result = (mac_result > target_max) ? target_max : // 상한선 돌파 시 고정
                              (mac_result < target_min) ? target_min : // 하한선 돌파 시 고정
                              mac_result;                            // 정상 범위 내 값 패스
    //INT4 연산 스케일에 맞춰서 Saturation 임계값을 2047로 맞춤
    // -------------------------------------------------------------------------
    // Pipeline Register 래칭 & Valid 생성 (순차회로)
    // -------------------------------------------------------------------------
    // 설명: 클록 상승 에지(posedge clk)에서만 작동하며, 날것의 데이터를 레지스터에 안전하게 담아 깨끗한 출력 신호로 내보냄. 이 과정에서 1클록의 타이밍 지연(latency) 발생

    always @(posedge clk or posedge reset) begin
        if (reset) begin
            // 리셋 상황 시 모든 출력 및 내부 레지스터를 0으로 초기화
            conv_out  <= 32'b0;
            valid_out <= 1'b0;
        end else begin
            // 파이프라인 레지스터를 거쳐 안정적인 신호 출력
            conv_out  <= saturated_result;
            // 입력 valid_d 신호를 1클록 지연시켜 valid_out으로 출력 (싱크 맞춤)
            valid_out <= valid_d;
        end
    end

endmodule

rtl/integration/reset_bridge.v
`timescale 1ns / 1ps
//=============================================================================
// File        : reset_bridge.v
// Description : Active-High(sync/async 혼용) reset -> Active-Low async reset
//               극성 변환 브릿지
//
// Design Notes:
//   - pe_ctrl 의 reset 은 posedge clk or posedge reset 감도리스트를 사용하므로
//     "비동기 assert, 이 always 블록 내에서 동기적으로 유지" 되는 표준 비동기
//     리셋 방식입니다. activation_unit 은 이를 Active-Low(reset_n)로 그대로
//     넘겨받기만 하면 되므로 단순 극성 반전(~reset)이 논리적으로는 충분합니다.
//   - 다만 두 모듈이 물리적으로 다른 위치/블록에 있을 가능성을 고려해,
//     리셋 해제(deassertion) 타이밍이 클럭 엣지에 깔끔히 정렬되도록
//     2-FF 동기화 방식의 "async assert / sync de-assert" 리셋 브릿지로
//     구성했습니다.
//   - Assert 시점은 즉시(비동기) 반영되므로 pe_ctrl 과 activation_unit 이
//     같은 사이클에 함께 리셋 상태로 들어갑니다. Deassert 만 1clk 늦게
//     풀리므로, 리셋 해제 후 첫 유효 데이터가 들어오기 전에 안전하게
//     reset_n 이 안정화됩니다(파이프라인 valid 흐름에는 영향 없음).
//=============================================================================
module reset_bridge (
    input  wire clk,
    input  wire reset,     // Active-High, pe_ctrl과 동일 클럭 도메인의 리셋
    output wire reset_n    // Active-Low, activation_unit 용
);

    reg sync0, sync1;

    always @(posedge clk or posedge reset) begin
        if (reset) begin
            // 비동기 assert : reset 이 뜨는 즉시 두 FF 모두 0으로 클리어
            sync0 <= 1'b0;
            sync1 <= 1'b0;
        end else begin
            // 동기 de-assert : 2단 시프트 후에만 reset_n = 1 로 해제
            sync0 <= 1'b1;
            sync1 <= sync0;
        end
    end

    assign reset_n = sync1;

endmodule

rtl/integration/pe_act_wrapper.v
`timescale 1ns / 1ps
//=============================================================================
// File        : pe_act_wrapper.v
// Description : pe_ctrl (Active-High reset, 32bit 정수 saturation)
//               -> activation_unit (Active-Low reset, 16bit Q8.8) 를
//               연결하는 최상위 래퍼
//
// 해결한 인터페이스 충돌:
//   1) 리셋 극성/방식 : reset_bridge 로 Active-High -> Active-Low(async) 변환
//   2) 비트 폭        : mac_to_q88_bridge 로 32bit -> 16bit 변환
//   3) 데이터 포맷     : 위 브릿지에서 모드별 정렬 시프트로 정수->Q8.8 변환
//   4) 제어 신호       : pe_ctrl 에 없던 enable / track_sel 을 wrapper 상위
//                        포트로 새로 노출하여 activation_unit 에 직접 연결
//
// Latency / Valid 동기화:
//   pe_ctrl        : mac_result/valid_d  -> conv_out/valid_out   : 1 clk (레지스터)
//   bit-width bridge : conv_out          -> data_q88             : 0 clk (조합)
//   activation_unit  : data_in/valid_in  -> data_out/valid_out   : 1 clk (레지스터)
//   ---------------------------------------------------------------
//   Total : mac_result 인가 시점 기준 data_out 까지 정확히 2 clk latency.
//
//   pe_ctrl 의 valid_out(=pe_valid_out) 을 브릿지를 거치지 않고 그대로
//   activation_unit 의 valid_in 에 조합적으로 연결했기 때문에, 데이터와
//   valid 가 항상 같은 사이클에 함께 이동합니다. 즉 별도의 valid 지연
//   보정 로직 없이도 두 파이프라인 스테이지가 정확히 1:1로 정렬됩니다.
//   (만약 추후 브릿지에 타이밍 클로징을 위한 레지스터 스테이지를 추가한다면,
//    반드시 pe_valid_out 도 동일하게 1clk 딜레이시켜 activation_unit 에
//    넣어줘야 valid-data 정렬이 깨지지 않습니다.)
//
// enable(pe_enable) 연결에 대한 저전력 설계 참고:
//   온디바이스 초저전력 NPU 특성상, activation_unit 의 enable 은 단순히
//   1'b1 로 고정하기보다 상위 시퀀서의 global enable 과 AND 해서 넣거나,
//   추후 클럭/데이터 게이팅과 결합해 valid 가 없는 구간에는 내부 토글을
//   줄이는 방향으로 확장하는 것을 권장합니다. 본 wrapper 는 이를 위해
//   pe_enable 을 상위에서 자유롭게 제어할 수 있도록 포트로 노출만
//   해두었습니다.
//=============================================================================
module pe_act_wrapper #(
    parameter DATA_WIDTH = 16,
    parameter FRAC_WIDTH = 8
)(
    // ---- 시스템 공통 ----
    input  wire                          clk,
    input  wire                          reset,      // Active-High (pe_ctrl 도메인 원본 리셋)
    input  wire                          mode_int4,  // 1: INT4 / 0: INT8

    // ---- pe_mac.v 로부터의 입력 (pe_ctrl 로 전달) ----
    input  wire signed [31:0]            mac_result,
    input  wire                          valid_d,

    // ---- activation_unit 제어용 신규 상위 포트 (기존에 누락되어 있던 신호) ----
    input  wire                          pe_enable,  // activation_unit enable
    input  wire                          track_sel,  // 0: ReLU(Feature) / 1: Sigmoid(Gate)

    // ---- 최종 출력 ----
    output wire signed [DATA_WIDTH-1:0]  data_out,
    output wire                          valid_out
);

    // 내부 연결 wire
    wire signed [31:0]           conv_out;
    wire                          pe_valid_out;
    wire                          reset_n;
    wire signed [DATA_WIDTH-1:0] bridged_data;

    //-------------------------------------------------------------------
    // 1) 리셋 브릿지
    //-------------------------------------------------------------------
    reset_bridge u_reset_bridge (
        .clk     (clk),
        .reset   (reset),
        .reset_n (reset_n)
    );

    //-------------------------------------------------------------------
    // 2) pe_ctrl 인스턴스 (원본 그대로, 수정 없음)
    //-------------------------------------------------------------------
    pe_ctrl u_pe_ctrl (
        .clk        (clk),
        .reset      (reset),
        .mode_int4  (mode_int4),
        .mac_result (mac_result),
        .valid_d    (valid_d),
        .conv_out   (conv_out),
        .valid_out  (pe_valid_out)
    );

    //-------------------------------------------------------------------
    // 3) 비트 폭 / 데이터 포맷 브릿지 (32bit 정수 -> 16bit Q8.8)
    //-------------------------------------------------------------------
    mac_to_q88_bridge #(
        .DATA_WIDTH (DATA_WIDTH),
        .FRAC_WIDTH (FRAC_WIDTH)
    ) u_mac_to_q88_bridge (
        .conv_out  (conv_out),
        .mode_int4 (mode_int4),
        .data_q88  (bridged_data)
    );

    //-------------------------------------------------------------------
    // 4) activation_unit 인스턴스 (원본 그대로, 수정 없음)
    //    - enable / track_sel 은 wrapper 신규 포트에서 직접 공급
    //    - valid_in 은 pe_valid_out 을 조합적으로 그대로 전달 (latency 정렬)
    //-------------------------------------------------------------------
    activation_unit #(
        .DATA_WIDTH (DATA_WIDTH),
        .FRAC_WIDTH (FRAC_WIDTH)
    ) u_activation_unit (
        .clk       (clk),
        .reset_n   (reset_n),
        .enable    (pe_enable),
        .track_sel (track_sel),
        .data_in   (bridged_data),
        .valid_in  (pe_valid_out),
        .data_out  (data_out),
        .valid_out (valid_out)
    );

endmodule

rtl/integration/tb_pe_act_wrapper.v
`timescale 1ns / 1ps
//=============================================================================
// File        : tb_pe_act_wrapper.v
// Description : pe_ctrl + bridge + activation_unit 통합 검증용 간단 TB
//
// 실행 방법 (로컬 PC, iverilog 설치 필요: apt-get install iverilog):
//   iverilog -g2012 -o sim.vvp \
//       pe_ctrl.v activation_unit.v reset_bridge.v \
//       mac_to_q88_bridge.v pe_act_wrapper.v tb_pe_act_wrapper.v
//   vvp sim.vvp
//   (GTKWave로 보고 싶으면 $dumpfile/$dumpvars 로 만든 wave.vcd 열기)
//=============================================================================
module tb_pe_act_wrapper;

    reg clk;
    reg reset;
    reg mode_int4;
    reg signed [31:0] mac_result;
    reg valid_d;
    reg pe_enable;
    reg track_sel;

    wire signed [15:0] data_out;
    wire valid_out;

    // 100MHz 가상 클록 (10ns 주기)
    initial clk = 0;
    always #5 clk = ~clk;

    pe_act_wrapper #(
        .DATA_WIDTH(16),
        .FRAC_WIDTH(8)
    ) DUT (
        .clk        (clk),
        .reset      (reset),
        .mode_int4  (mode_int4),
        .mac_result (mac_result),
        .valid_d    (valid_d),
        .pe_enable  (pe_enable),
        .track_sel  (track_sel),
        .data_out   (data_out),
        .valid_out  (valid_out)
    );

    // 편의상 결과를 실수로 환산해서 같이 출력 (Q8.8 -> real)
    real data_out_real;
    always @(*) data_out_real = data_out / 256.0;

    // 입력 인가 후 몇 클럭 뒤에 결과가 나오는지 눈으로 확인하기 위한 로그
    always @(posedge clk) begin
        $display("t=%0t | reset=%b mode_int4=%b track_sel=%b | mac_result=%0d valid_d=%b || data_out=%0d (%f) valid_out=%b",
                   $time, reset, mode_int4, track_sel, mac_result, valid_d, data_out, data_out_real, valid_out);
    end

    initial begin
        $dumpfile("wave.vcd");
        $dumpvars(0, tb_pe_act_wrapper);

        // ---- 초기화 / 리셋 ----
        reset      = 1'b1;
        mode_int4  = 1'b0;   // INT8 모드로 시작
        mac_result = 32'sd0;
        valid_d    = 1'b0;
        pe_enable  = 1'b1;
        track_sel  = 1'b0;   // ReLU
        repeat (3) @(posedge clk);
        reset = 1'b0;
        @(posedge clk);

        // ---- Case 1 : INT8 모드, 정상 범위 양수, ReLU ----
        mode_int4  = 1'b0;
        track_sel  = 1'b0;      // ReLU
        mac_result = 32'sd100000;
        valid_d    = 1'b1;
        @(posedge clk);
        valid_d    = 1'b0;
        repeat (4) @(posedge clk);

        // ---- Case 2 : INT8 모드, saturation 유발 (상한 초과), Sigmoid ----
        mode_int4  = 1'b0;
        track_sel  = 1'b1;      // Sigmoid
        mac_result = 32'sd900000;   // target_max(524287) 초과 -> saturation 확인
        valid_d    = 1'b1;
        @(posedge clk);
        valid_d    = 1'b0;
        repeat (4) @(posedge clk);

        // ---- Case 3 : INT4 모드, 정상 범위 음수, ReLU ----
        mode_int4  = 1'b1;
        track_sel  = 1'b0;      // ReLU
        mac_result = -32'sd1500;
        valid_d    = 1'b1;
        @(posedge clk);
        valid_d    = 1'b0;
        repeat (4) @(posedge clk);

        // ---- Case 4 : INT4 모드, 상한 초과(saturation), Sigmoid ----
        mode_int4  = 1'b1;
        track_sel  = 1'b1;      // Sigmoid
        mac_result = 32'sd3000;     // target_max(2047) 초과 -> saturation 확인
        valid_d    = 1'b1;
        @(posedge clk);
        valid_d    = 1'b0;
        repeat (4) @(posedge clk);

        // ---- Case 5 : enable=0 일 때 valid가 죽는지 확인 ----
        pe_enable  = 1'b0;
        mode_int4  = 1'b0;
        mac_result = 32'sd50000;
        valid_d    = 1'b1;
        @(posedge clk);
        valid_d    = 1'b0;
        pe_enable  = 1'b1;
        repeat (4) @(posedge clk);

        $display("TEST DONE");
        $finish;
    end

endmodule

rtl/integration/wave.vcd
$date
	Sat Jul  4 17:32:21 2026
$end
$version
	Icarus Verilog
$end
$timescale
	1ps
$end
$scope module tb_pe_act_wrapper $end
$var wire 1 ! valid_out $end
$var wire 16 " data_out [15:0] $end
$var reg 1 # clk $end
$var reg 32 $ mac_result [31:0] $end
$var reg 1 % mode_int4 $end
$var reg 1 & pe_enable $end
$var reg 1 ' reset $end
$var reg 1 ( track_sel $end
$var reg 1 ) valid_d $end
$var real 1 * data_out_real $end
$scope module DUT $end
$var wire 1 # clk $end
$var wire 32 + mac_result [31:0] $end
$var wire 1 % mode_int4 $end
$var wire 1 & pe_enable $end
$var wire 1 ' reset $end
$var wire 1 ( track_sel $end
$var wire 1 ) valid_d $end
$var wire 1 ! valid_out $end
$var wire 1 , reset_n $end
$var wire 1 - pe_valid_out $end
$var wire 16 . data_out [15:0] $end
$var wire 32 / conv_out [31:0] $end
$var wire 16 0 bridged_data [15:0] $end
$var parameter 32 1 DATA_WIDTH $end
$var parameter 32 2 FRAC_WIDTH $end
$scope module u_activation_unit $end
$var wire 1 # clk $end
$var wire 1 & enable $end
$var wire 1 ( track_sel $end
$var wire 1 - valid_in $end
$var wire 16 3 shifted_x [15:0] $end
$var wire 1 , reset_n $end
$var wire 16 4 data_in [15:0] $end
$var parameter 32 5 DATA_WIDTH $end
$var parameter 16 6 FP_HALF $end
$var parameter 16 7 FP_ONE $end
$var parameter 16 8 FP_ZERO $end
$var parameter 32 9 FRAC_WIDTH $end
$var parameter 16 : NEG_THRESHOLD $end
$var parameter 16 ; POS_THRESHOLD $end
$var reg 16 < act_result_comb [15:0] $end
$var reg 16 = data_out [15:0] $end
$var reg 16 > relu_result [15:0] $end
$var reg 16 ? sigmoid_result [15:0] $end
$var reg 1 ! valid_out $end
$upscope $end
$scope module u_mac_to_q88_bridge $end
$var wire 1 % mode_int4 $end
$var wire 32 @ shifted_val [31:0] $end
$var wire 16 A data_q88 [15:0] $end
$var wire 32 B conv_out [31:0] $end
$var wire 32 C clipped_val [31:0] $end
$var parameter 32 D DATA_WIDTH $end
$var parameter 32 E FRAC_WIDTH $end
$var parameter 32 F Q88_MAX $end
$var parameter 32 G Q88_MIN $end
$var parameter 32 H SHIFT_AMT $end
$upscope $end
$scope module u_pe_ctrl $end
$var wire 1 # clk $end
$var wire 32 I mac_result [31:0] $end
$var wire 1 % mode_int4 $end
$var wire 1 ' reset $end
$var wire 1 ) valid_d $end
$var wire 32 J target_min [31:0] $end
$var wire 32 K target_max [31:0] $end
$var wire 32 L saturated_result [31:0] $end
$var reg 32 M conv_out [31:0] $end
$var reg 1 - valid_out $end
$upscope $end
$scope module u_reset_bridge $end
$var wire 1 # clk $end
$var wire 1 ' reset $end
$var wire 1 , reset_n $end
$var reg 1 N sync0 $end
$var reg 1 O sync1 $end
$upscope $end
$upscope $end
$upscope $end
$enddefinitions $end
$comment Show the parameter values. $end
$dumpall
b100 H
b11111111111111111000000000000000 G
b111111111111111 F
b1000 E
b10000 D
b10000000000 ;
b1111110000000000 :
b1000 9
b0 8
b100000000 7
b10000000 6
b10000 5
b1000 2
b10000 1
$end
#0
$dumpvars
0O
0N
b0 M
b0 L
b1111111111111111111 K
b11111111111110000000000000000001 J
b0 I
b0 C
b0 B
b0 A
b0 @
b10000000 ?
b0 >
b0 =
b0 <
b0 4
b0 3
b0 0
b0 /
b0 .
0-
0,
b0 +
r0 *
0)
0(
1'
1&
0%
b0 $
0#
b0 "
0!
$end
#5000
1#
#10000
0#
#15000
1#
#20000
0#
#25000
1N
0'
1#
#30000
0#
#35000
1,
1O
1-
b11000011010100000 L
1)
b11000011010100000 $
b11000011010100000 +
b11000011010100000 I
1#
#40000
0#
#45000
b1100001101010 <
b1100001101 3
b100000000 ?
b1100001101010 >
b1100001101010 0
b1100001101010 4
b1100001101010 A
b1100001101010 C
b1100001101010 @
1!
0-
b11000011010100000 /
b11000011010100000 B
b11000011010100000 M
0)
1#
#50000
0#
#55000
r24.4140625 *
0!
b1100001101010 "
b1100001101010 .
b1100001101010 =
1#
#60000
0#
#65000
1#
#70000
0#
#75000
1#
#80000
0#
#85000
1-
b1111111111111111111 L
b100000000 <
1)
b11011011101110100000 $
b11011011101110100000 +
b11011011101110100000 I
1(
1#
#90000
0#
#95000
b111111111111 3
b111111111111111 >
b111111111111111 0
b111111111111111 4
b111111111111111 A
b111111111111111 C
b111111111111111 @
r1 *
1!
b100000000 "
b100000000 .
b100000000 =
0-
b1111111111111111111 /
b1111111111111111111 B
b1111111111111111111 M
0)
1#
#100000
0#
#105000
0!
1#
#110000
0#
#115000
1#
#120000
0#
#125000
1#
#130000
0#
#135000
1-
b11111111111111111111101000100100 L
b111111111111111 <
b11111111111111111110000 @
b11111111111 K
b11111111111111111111100000000001 J
1)
b11111111111111111111101000100100 $
b11111111111111111111101000100100 +
b11111111111111111111101000100100 I
0(
1%
1#
#140000
0#
#145000
b0 <
b1111010001001000 3
b0 ?
b0 >
b1010001001000000 0
b1010001001000000 4
b1010001001000000 A
b11111111111111111010001001000000 C
b11111111111111111010001001000000 @
r127.99609375 *
1!
b111111111111111 "
b111111111111111 .
b111111111111111 =
0-
b11111111111111111111101000100100 /
b11111111111111111111101000100100 B
b11111111111111111111101000100100 M
0)
1#
#150000
0#
#155000
r0 *
0!
b0 "
b0 .
b0 =
1#
#160000
0#
#165000
1#
#170000
0#
#175000
1#
#180000
0#
#185000
1-
b11111111111 L
1)
b101110111000 $
b101110111000 +
b101110111000 I
1(
1#
#190000
0#
#195000
b100000000 <
b111111111110 3
b100000000 ?
b111111111110000 >
b111111111110000 0
b111111111110000 4
b111111111110000 A
b111111111110000 C
b111111111110000 @
1!
0-
b11111111111 /
b11111111111 B
b11111111111 M
0)
1#
#200000
0#
#205000
r1 *
0!
b100000000 "
b100000000 .
b100000000 =
1#
#210000
0#
#215000
1#
#220000
0#
#225000
1#
#230000
0#
#235000
1-
b10001111 <
b1111 3
b10001111 ?
b1111111 >
b1111111 0
b1111111 4
b1111111 A
b1111111 C
b1100001101010000 L
b1111111 @
b1111111111111111111 K
b11111111111110000000000000000001 J
1)
b1100001101010000 $
b1100001101010000 +
b1100001101010000 I
0%
0&
1#
#240000
0#
#245000
b100000000 <
b110000110 3
b100000000 ?
b110000110101 >
b110000110101 0
b110000110101 4
b110000110101 A
b110000110101 C
b110000110101 @
r0.55859375 *
1!
b10001111 "
b10001111 .
b10001111 =
0-
b1100001101010000 /
b1100001101010000 B
b1100001101010000 M
1&
0)
1#
#250000
0#
#255000
r1 *
0!
b100000000 "
b100000000 .
b100000000 =
1#
